[
  {
    "Id": 1,
    "Name": "Discrete signal mapping 1",
    "DiscreteValueToState": 
    {
      "00": "Error",
      "11": "Transit",
      "01": "Open",
      "10": "Close" 
    }
  },
  {
    "Id": 2,
    "Name": "Discrete signal mapping 2",
    "DiscreteValueToState": {
      "00": "Error",
      "11": "Transit",
      "01": "On",
      "10": "Off"
    }
  },
  {
    "Id": 3,
    "Name": "Discrete signal mapping 3",
    "DiscreteValueToState": {
      "1": "On",
      "0": "Off"
    }
  }
]